ll2cz/__init__.py
ll2cz/__main__.py
ll2cz/analysis.py
ll2cz/cache.py
ll2cz/cached_database.py
ll2cz/cbf_builder.py
ll2cz/cbf_transformer.py
ll2cz/chunked_processor.py
ll2cz/cli.py
ll2cz/config/providers.yml
ll2cz/config.py
ll2cz/czrn.py
ll2cz/data_processor.py
ll2cz/data_source_strategy.py
ll2cz/database.py
ll2cz/database_original.py
ll2cz/date_utils.py
ll2cz/decorators.py
ll2cz/error_tracking.py
ll2cz/model_name_strategies.py
ll2cz/output.py
ll2cz/transform.py
ll2cz/transformations.py
ll2cz/transmit.py
ll2cz/transmit_refactored.py
ll2cz-0.6.2.dist-info/WHEEL
ll2cz-0.6.2.dist-info/entry_points.txt
ll2cz-0.6.2.dist-info/METADATA
ll2cz-0.6.2.dist-info/RECORD
