Metadata-Version: 2.3
Name: ll2cz
Version: 0.6.2
Summary: Transform LiteLLM database data into CloudZero AnyCost CBF format
Keywords: litellm,cloudzero,etl,cost-management,billing
Author: Erik Peterson
Author-email: Erik Peterson <erik@cloudzero.com>
License: Apache-2.0
Classifier: Development Status :: 4 - Beta
Classifier: Intended Audience :: Developers
Classifier: Intended Audience :: System Administrators
Classifier: License :: OSI Approved :: Apache Software License
Classifier: Operating System :: OS Independent
Classifier: Programming Language :: Python :: 3
Classifier: Programming Language :: Python :: 3.9
Classifier: Programming Language :: Python :: 3.10
Classifier: Programming Language :: Python :: 3.11
Classifier: Programming Language :: Python :: 3.12
Classifier: Programming Language :: Python :: 3.13
Classifier: Topic :: Office/Business :: Financial
Classifier: Topic :: System :: Systems Administration
Classifier: Topic :: Utilities
Requires-Dist: psycopg[binary]>=3.1.0
Requires-Dist: polars>=0.20.0
Requires-Dist: httpx>=0.25.0
Requires-Dist: connectorx>=0.3.0
Requires-Dist: pyyaml>=6.0.0
Requires-Dist: rich>=13.0.0
Requires-Dist: litellm>=1.74.7
Requires-Python: >=3.9
Project-URL: Changelog, https://github.com/Cloudzero/cloudzero-litellm-toolkit/blob/main/CHANGELOG.md
Project-URL: Documentation, https://github.com/Cloudzero/cloudzero-litellm-toolkit/blob/main/README.md
Project-URL: Homepage, https://github.com/Cloudzero/cloudzero-litellm-toolkit
Project-URL: Issues, https://github.com/Cloudzero/cloudzero-litellm-toolkit/issues
Project-URL: Repository, https://github.com/Cloudzero/cloudzero-litellm-toolkit.git
